fspot_werkzeug-0.13.dev0.dist-info/DESCRIPTION.rst
fspot_werkzeug-0.13.dev0.dist-info/LICENSE.txt
fspot_werkzeug-0.13.dev0.dist-info/METADATA
fspot_werkzeug-0.13.dev0.dist-info/RECORD
fspot_werkzeug-0.13.dev0.dist-info/WHEEL
fspot_werkzeug-0.13.dev0.dist-info/metadata.json
fspot_werkzeug-0.13.dev0.dist-info/top_level.txt
werkzeug/__init__.py
werkzeug/_compat.py
werkzeug/_internal.py
werkzeug/_reloader.py
werkzeug/datastructures.py
werkzeug/exceptions.py
werkzeug/filesystem.py
werkzeug/formparser.py
werkzeug/http.py
werkzeug/local.py
werkzeug/posixemulation.py
werkzeug/routing.py
werkzeug/security.py
werkzeug/serving.py
werkzeug/test.py
werkzeug/testapp.py
werkzeug/urls.py
werkzeug/useragents.py
werkzeug/utils.py
werkzeug/wrappers.py
werkzeug/wsgi.py
werkzeug/contrib/__init__.py
werkzeug/contrib/atom.py
werkzeug/contrib/cache.py
werkzeug/contrib/fixers.py
werkzeug/contrib/iterio.py
werkzeug/contrib/jsrouting.py
werkzeug/contrib/limiter.py
werkzeug/contrib/lint.py
werkzeug/contrib/profiler.py
werkzeug/contrib/securecookie.py
werkzeug/contrib/sessions.py
werkzeug/contrib/testtools.py
werkzeug/contrib/wrappers.py
werkzeug/debug/__init__.py
werkzeug/debug/console.py
werkzeug/debug/repr.py
werkzeug/debug/tbtools.py
werkzeug/debug/shared/FONT_LICENSE
werkzeug/debug/shared/console.png
werkzeug/debug/shared/debugger.js
werkzeug/debug/shared/jquery.js
werkzeug/debug/shared/less.png
werkzeug/debug/shared/more.png
werkzeug/debug/shared/source.png
werkzeug/debug/shared/style.css
werkzeug/debug/shared/ubuntu.ttf
