Metadata-Version: 2.0
Name: fspot-werkzeug
Version: 0.13.dev0
Summary: The Swiss Army knife of Python web development
Home-page: http://werkzeug.pocoo.org/
Author: Armin Ronacher
Author-email: armin.ronacher@active-4.com
License: BSD
Platform: any
Classifier: Development Status :: 5 - Production/Stable
Classifier: Environment :: Web Environment
Classifier: Intended Audience :: Developers
Classifier: License :: OSI Approved :: BSD License
Classifier: Operating System :: OS Independent
Classifier: Programming Language :: Python
Classifier: Programming Language :: Python :: 2
Classifier: Programming Language :: Python :: 2.6
Classifier: Programming Language :: Python :: 2.7
Classifier: Programming Language :: Python :: 3
Classifier: Programming Language :: Python :: 3.3
Classifier: Programming Language :: Python :: 3.4
Classifier: Programming Language :: Python :: 3.5
Classifier: Topic :: Internet :: WWW/HTTP :: Dynamic Content
Classifier: Topic :: Software Development :: Libraries :: Python Modules
Provides-Extra: termcolor
Requires-Dist: termcolor; extra == 'termcolor'
Provides-Extra: watchdog
Requires-Dist: watchdog; extra == 'watchdog'
